kea_exporter-0.7.0.dist-info/METADATA
kea_exporter-0.7.0.dist-info/WHEEL
kea_exporter-0.7.0.dist-info/entry_points.txt
kea_exporter-0.7.0.dist-info/licenses/LICENSE
kea_exporter/__init__.py
kea_exporter/__main__.py
kea_exporter/cli.py
kea_exporter/exporter.py
kea_exporter/http.py
kea_exporter/uds.py
kea_exporter-0.7.0.dist-info/RECORD
