Metadata-Version: 2.1
Name: kea-exporter
Version: 0.7.0
Summary: Export Kea Metrics in the Prometheus Exposition Format
Keywords: prometheus exporter metrics kea dhcp
Home-page: https://github.com/mweinelt/kea-exporter
Author-Email: Martin Weinelt <hexa@darmstadt.ccc.de>
License: MIT
Classifier: Development Status :: 5 - Production/Stable
Classifier: License :: OSI Approved :: MIT License
Classifier: Programming Language :: Python :: 3.8
Classifier: Programming Language :: Python :: 3.9
Classifier: Programming Language :: Python :: 3.10
Classifier: Programming Language :: Python :: 3.11
Classifier: Programming Language :: Python :: 3.12
Classifier: Topic :: System :: Monitoring
Classifier: Topic :: System :: Systems Administration
Project-URL: Changelog, https://github.com/mweinelt/kea-exporter/blob/develop/HISTORY
Project-URL: Homepage, https://github.com/mweinelt/kea-exporter
Project-URL: Repository, https://github.com/mweinelt/kea-exporter.git
Requires-Python: <4.0,>=3.8
Requires-Dist: click<9.0,>=8.1.7
Requires-Dist: prometheus-client<1.0,>=0.20.0
Requires-Dist: requests<3.0,>=2.31.0
